tcms_pytest_plugin/__init__.py
tcms_pytest_plugin/version.py
kiwitcms_pytest_plugin-12.8.1.dist-info/LICENSE
kiwitcms_pytest_plugin-12.8.1.dist-info/METADATA
kiwitcms_pytest_plugin-12.8.1.dist-info/WHEEL
kiwitcms_pytest_plugin-12.8.1.dist-info/entry_points.txt
kiwitcms_pytest_plugin-12.8.1.dist-info/top_level.txt
kiwitcms_pytest_plugin-12.8.1.dist-info/RECORD
